garpix_favourite/CHANGELOG.md
garpix_favourite/CONTRIBUTING.md
garpix_favourite/MANIFEST.in
garpix_favourite/README.md
garpix_favourite/__init__.py
garpix_favourite/apps.py
garpix_favourite/models.py
garpix_favourite/routers.py
garpix_favourite/serializers.py
garpix_favourite/setup.py
garpix_favourite/tests.py
garpix_favourite/urls.py
garpix_favourite/utils.py
garpix_favourite/views.py
garpix_favourite/__pycache__/__init__.cpython-38.pyc
garpix_favourite/__pycache__/apps.cpython-38.pyc
garpix_favourite/__pycache__/models.cpython-38.pyc
garpix_favourite/__pycache__/routers.cpython-38.pyc
garpix_favourite/__pycache__/serializers.cpython-38.pyc
garpix_favourite/__pycache__/urls.cpython-38.pyc
garpix_favourite/__pycache__/views.cpython-38.pyc
garpix_favourite/admin/__init__.py
garpix_favourite/admin/favorite.py
garpix_favourite/admin/__pycache__/__init__.cpython-38.pyc
garpix_favourite/admin/__pycache__/favorite.cpython-38.pyc
garpix_favourite-2.2.0.dist-info/METADATA
garpix_favourite-2.2.0.dist-info/WHEEL
garpix_favourite-2.2.0.dist-info/top_level.txt
garpix_favourite-2.2.0.dist-info/RECORD
